<TaskerData sr="" dvi="1" tv="4.9u4m">
	<Profile sr="prof4" ve="2">
		<cdate>1500413288030</cdate>
		<edate>1500413309814</edate>
		<id>4</id>
		<mid0>2</mid0>
		<nme>Lid State Changed</nme>
		<Event sr="con0" ve="2">
			<code>599</code>
			<pri>0</pri>
			<Str sr="arg0" ve="3">android.intent.action.LID_EVENT</Str>
			<Int sr="arg1" val="0"/>
			<Int sr="arg2" val="0"/>
			<Str sr="arg3" ve="3"/>
			<Str sr="arg4" ve="3"/>
		</Event>
	</Profile>
	<Task sr="task2">
		<cdate>1500401451133</cdate>
		<edate>1500413379780</edate>
		<id>2</id>
		<nme>lock_screen</nme>
		<Action sr="act0" ve="7">
			<code>1563799945</code>
			<Bundle sr="arg0">
				<Vals sr="val">
					<com.intangibleobject.securesettings.plugin.extra.BLURB>Lock Device</com.intangibleobject.securesettings.plugin.extra.BLURB>
					<com.intangibleobject.securesettings.plugin.extra.BLURB-type>java.lang.String</com.intangibleobject.securesettings.plugin.extra.BLURB-type>
					<com.intangibleobject.securesettings.plugin.extra.SETTING>force_lock</com.intangibleobject.securesettings.plugin.extra.SETTING>
					<com.intangibleobject.securesettings.plugin.extra.SETTING-type>java.lang.String</com.intangibleobject.securesettings.plugin.extra.SETTING-type>
					<com.twofortyfouram.locale.intent.extra.BLURB>Lock Device</com.twofortyfouram.locale.intent.extra.BLURB>
					<com.twofortyfouram.locale.intent.extra.BLURB-type>java.lang.String</com.twofortyfouram.locale.intent.extra.BLURB-type>
					<net.dinglisch.android.tasker.subbundled>true</net.dinglisch.android.tasker.subbundled>
					<net.dinglisch.android.tasker.subbundled-type>java.lang.Boolean</net.dinglisch.android.tasker.subbundled-type>
				</Vals>
			</Bundle>
			<Str sr="arg1" ve="3">com.intangibleobject.securesettings.plugin</Str>
			<Str sr="arg2" ve="3">com.intangibleobject.securesettings.plugin.Activities.TabsActivity</Str>
			<Int sr="arg3" val="0"/>
			<ConditionList sr="if">
				<Condition sr="c0" ve="3">
					<lhs>%android_intent_extra_lid_state</lhs>
					<op>0</op>
					<rhs>1</rhs>
				</Condition>
			</ConditionList>
		</Action>
	</Task>
</TaskerData>
